LICENSE
README.md
baseresources/favicon-32x32.png
baseresources/local.css
baseresources/sedrila.css
baseresources/sidebar.js
base.py
cache.py
mycrypt.py
sdrl/__init__.py
sdrl/argparser.py
sdrl/constants.py
sdrl/course.py
sdrl/directory.py
sdrl/elements.py
sdrl/glossary.py
sdrl/html.py
sdrl/linkchecker.py
sdrl/macroexpanders.py
sdrl/macros.py
sdrl/markdown.py
sdrl/partbuilder.py
sdrl/participant.py
sdrl/programchecker.py
sdrl/protocolchecker.py
sdrl/rename.py
sdrl/replacements.py
sdrl/repo.py
sdrl/snippetchecker.py
sdrl/subcmd/__init__.py
sdrl/subcmd/author.py
sdrl/subcmd/evaluator.py
sdrl/subcmd/instructor.py
sdrl/subcmd/maintainer.py
sdrl/subcmd/server.py
sdrl/subcmd/student.py
sdrl/webapp.py
sedrila.py
sgit.py
pyproject.toml
templates/base.html
templates/chapter.html
templates/glossary.html
templates/homepage.html
templates/task.html
templates/taskgroup.html
sedrila-2.10.2.dist-info/LICENSE
sedrila-2.10.2.dist-info/METADATA
sedrila-2.10.2.dist-info/WHEEL
sedrila-2.10.2.dist-info/entry_points.txt
sedrila-2.10.2.dist-info/RECORD
