Metadata-Version: 2.1
Name: sedrila
Version: 2.10.2
Summary: Tool infrastructure for building and running "self-driven lab" courses
Home-page: https://github.com/fubinf/sedrila
License: MIT
Keywords: static site generator, learning management system
Author: Lutz Prechelt
Author-email: prechelt@inf.fu-berlin.de
Requires-Python: >=3.11,<4.0
Classifier: Development Status :: 5 - Production/Stable
Classifier: Environment :: Console
Classifier: Environment :: Web Environment
Classifier: Intended Audience :: Education
Classifier: License :: OSI Approved :: MIT License
Classifier: Operating System :: Unix
Classifier: Programming Language :: Python :: 3
Classifier: Programming Language :: Python :: 3.11
Classifier: Topic :: Documentation
Classifier: Topic :: Education :: Computer Aided Instruction (CAI)
Classifier: Topic :: Software Development :: Build Tools
Classifier: Topic :: Software Development :: Documentation
Classifier: Topic :: Text Processing :: Markup
Classifier: Topic :: Text Processing :: Markup :: Markdown
Requires-Dist: GitPython (>=3.1,<4.0)
Requires-Dist: Jinja2 (>=3.1,<4.0)
Requires-Dist: Markdown (>=3.7,<4.0)
Requires-Dist: PyYAML (>=6.0,<7.0)
Requires-Dist: Pygments (>=2.17,<3.0)
Requires-Dist: argparse_subcommand (>=1.2,<2.0)
Requires-Dist: blessed (>=1.20,<2.0)
Requires-Dist: bottle (>=0.13,<0.14)
Requires-Dist: matplotlib (>=3.9,<4.0)
Requires-Dist: mdx_linkify (>=2.1,<3.0)
Requires-Dist: numpy (<2)
Requires-Dist: pandas (>=2.2,<3.0)
Requires-Dist: python-gnupg (>=0.5.5,<0.6.0)
Requires-Dist: requests (>=2.32,<3.0)
Requires-Dist: rich (>=13.7,<14.0)
Project-URL: Repository, https://github.com/fubinf/sedrila
